README.rst
setup.py
denis/__init__.py
denis/models.py
django_denis.egg-info/PKG-INFO
django_denis.egg-info/SOURCES.txt
django_denis.egg-info/dependency_links.txt
django_denis.egg-info/not-zip-safe
django_denis.egg-info/requires.txt
django_denis.egg-info/top_level.txt